percents/__init__.py
percents/percent_type.py
tests/__init__.py
tests/test_percent.py
percents-1.2.3.dist-info/METADATA
percents-1.2.3.dist-info/WHEEL
percents-1.2.3.dist-info/top_level.txt
percents-1.2.3.dist-info/RECORD
