Metadata-Version: 2.1
Name: percents
Version: 1.2.3
Summary: UNKNOWN
Home-page: UNKNOWN
License: UNKNOWN
Platform: UNKNOWN
